LICENSE
MANIFEST.in
README.md
README.rst
setup.py
korr/__init__.py
korr/bootcorr.py
korr/bracket_pval.py
korr/confusion.py
korr/corr_vs_pval.py
korr/corrgram.py
korr/find_best.py
korr/find_unrelated.py
korr/find_worst.py
korr/flatten.py
korr/kendall.py
korr/mcc.py
korr/mincorr.py
korr/pearson.py
korr/slice_yx.py
korr/spearman.py
korr.egg-info/PKG-INFO
korr.egg-info/SOURCES.txt
korr.egg-info/dependency_links.txt
korr.egg-info/requires.txt
korr.egg-info/top_level.txt
korr.egg-info/zip-safe
test/__init__.py
test/test_kendall.py
test/test_mcc.py
test/test_pearson.py
test/test_spearman.py