Metadata-Version: 2.1
Name: korr
Version: 0.10.0
Summary: collection of utility functions for correlation analysis
Home-page: http://github.com/kmedian/korr
Author: Ulf Hamster
Author-email: 554c46@gmail.com
License: Apache License 2.0
Requires-Python: >=3.7
License-File: LICENSE
